meds_evaluation/__init__.py
meds_evaluation/__main__.py
meds_evaluation/evaluate.py
meds_evaluation/schema.py
meds_evaluation/utils.py
meds_evaluation/configs/__init__.py
meds_evaluation/configs/meds_evaluation.yaml
meds_evaluation-0.0.4.dist-info/licenses/LICENSE
meds_evaluation-0.0.4.dist-info/METADATA
meds_evaluation-0.0.4.dist-info/WHEEL
meds_evaluation-0.0.4.dist-info/entry_points.txt
meds_evaluation-0.0.4.dist-info/top_level.txt
meds_evaluation-0.0.4.dist-info/RECORD
