Metadata-Version: 2.4
Name: meds-evaluation
Version: 0.0.4
Summary: A module for evaluating the predictions of the models trained on MEDS datasets.
Author-email: Kamilė Stankevičiūtė <kamile.stankeviciute@cst.cam.ac.uk>, Vincent Jeanselme <vincent.jeanselme@mrc-bsu.cam.ac.uk>, Matthew McDermott <mattmcdermott8@gmail.com>
Project-URL: Homepage, https://github.com/kamilest/meds-evaluation
Project-URL: Issues, https://github.com/kamilest/meds-evaluation/issues
Classifier: Development Status :: 3 - Alpha
Classifier: Programming Language :: Python :: 3
Classifier: License :: OSI Approved :: MIT License
Classifier: Operating System :: OS Independent
Requires-Python: >=3.10
License-File: LICENSE
Requires-Dist: polars~=1.27.0
Requires-Dist: pyarrow
Requires-Dist: numpy
Requires-Dist: scikit-learn
Requires-Dist: hydra-core
Requires-Dist: meds~=0.4.0
Requires-Dist: flexible_schema
Provides-Extra: dev
Requires-Dist: pre-commit<4; extra == "dev"
Provides-Extra: tests
Requires-Dist: pytest; extra == "tests"
Requires-Dist: pytest-cov; extra == "tests"
Dynamic: license-file
